{
  "article_number": "376",
  "source": "Code de Travail Tunisien",
  "text": "Article 376 (Modifié par la loi n° 76-84 du 11 août 1976 puis par la loi n° 94-29 du 21 février 1994). Toute difficulté surgie entre l'employeur et les travailleurs, susceptible de provoquer un conflit collectif, doit être soumise à la commission consultative d'entreprise en vue de lui trouver des solutions convenant aux deux parties au conflit. Si le conflit n'a pas été résolu au sein de l'entreprise, il sera obligatoirement soumis par la partie la plus diligente au bureau régional de conciliation et à défaut à l'inspection du travail territorialement compétente.",
  "chapter_number": "XIII",
  "chapter_title": "Règlement des conflits collectifs de travail",
  "modified_by": " 76-84 du 11 août 1976 puis par la loi n° 94-29 du 21 février 1994"
}