{
  "article_number": "310",
  "source": "Code de Travail Tunisien",
  "text": "Article 310 (Modifié par la loi n° 96-62 du 15 juillet 1996). Dans le cas où le fonctionnement d'établissements industriels dûment autorisés, d'établissements dont l'existence est antérieure au classement de l'industrie à laquelle ils appartiennent ou d'établissements industriels non compris dans la nomenclature des établissements classés, présente un préjudice ou un danger graves pour les travailleurs ou le voisinage ou pour la santé publique, que les mesures prévues au présent chapitre et aux textes pris pour son applications ne seraient pas susceptibles de faire disparaître, ces établissements peuvent être fermés définitivement par arrêté du ministre chargé de l'industrie, pris après avis du comité spécial des établissements dangereux, insalubres ou incommodes. Section III Formalités relatives aux demandes d'ouverture des établissements classés",
  "chapter_number": "VI",
  "chapter_title": "Les établissements dangereux, insalubres ou incommodes Section I Classification des établissements dangereux, insalubres ou incommodes",
  "modified_by": " 96-62 du 15 juillet 1996"
}